setup.py
fkglib/__init__.py
fkglib/one.py
fkglib/two.py
fkglib.egg-info/PKG-INFO
fkglib.egg-info/SOURCES.txt
fkglib.egg-info/dependency_links.txt
fkglib.egg-info/top_level.txt