Metadata-Version: 2.1
Name: fkglib
Version: 0.0.1
Summary: Legend
Author: Filippov Konstantin Grigor'evich
Author-email: 40381@gmail.com
